.DS_Store
simplendb/__init__.py
simplendb/helpers.py
simplendb/images.py
simplendb/ndb.py
simplendb/users.py
simpleNDB-1.0.6.dist-info/LICENSE
simpleNDB-1.0.6.dist-info/METADATA
simpleNDB-1.0.6.dist-info/WHEEL
simpleNDB-1.0.6.dist-info/top_level.txt
simpleNDB-1.0.6.dist-info/RECORD
