Metadata-Version: 2.1
Name: simpleNDB
Version: 1.0.6
Summary: A very simple package to make Google Cloud Clients look more like appengine.api and NDB
Home-page: https://github.com/runette/simpleNDB
Author: Paul Harwood
Author-email: runette@gmail.com
License: UNKNOWN
Platform: UNKNOWN
Classifier: Programming Language :: Python :: 3.4
Classifier: Programming Language :: Python :: 3.5
Classifier: Programming Language :: Python :: 3.6
Classifier: Programming Language :: Python :: 3.7
Classifier: License :: OSI Approved :: MIT License
Classifier: Operating System :: OS Independent
Requires-Dist: grpcio
Requires-Dist: google-cloud-datastore
Requires-Dist: google-cloud-storage
Requires-Dist: Pillow
Requires-Dist: attrdict
